triecli/__init__.py
triecli/cli.py
trie_cli-0.1.3.dist-info/LICENSE.txt
trie_cli-0.1.3.dist-info/METADATA
trie_cli-0.1.3.dist-info/WHEEL
trie_cli-0.1.3.dist-info/entry_points.txt
trie_cli-0.1.3.dist-info/top_level.txt
trie_cli-0.1.3.dist-info/RECORD
