Metadata-Version: 2.1
Name: trie-cli
Version: 0.1.3
Summary: A CLI to interact with a global trie data structure.
Home-page: https://github.com/pmathur007/trie-cli
Author: Pranav Mathur
Author-email: pranavmathur001@gmail.com
License: UNKNOWN
Platform: UNKNOWN
Classifier: Programming Language :: Python :: 3
Classifier: License :: OSI Approved :: MIT License
Classifier: Operating System :: MacOS
Requires-Dist: click (==7.1.2)
Requires-Dist: requests (==2.25.1)
